swiflow-0.0.1.dist-info/METADATA
swiflow-0.0.1.dist-info/WHEEL
swiflow-0.0.1.dist-info/licenses/LICENSE
swiflow.libs/libgcc_s-5b5488a6.so.1
swiflow/__init__.py
swiflow/_common.py
swiflow/_impl.abi3.so
swiflow/_impl/__init__.pyi
swiflow/_impl/flow.pyi
swiflow/_impl/gflow.pyi
swiflow/_impl/pflow.pyi
swiflow/common.py
swiflow/flow.py
swiflow/gflow.py
swiflow/pflow.py
swiflow/py.typed
swiflow-0.0.1.dist-info/RECORD
